setup.py
src/mousedb/__init__.py
src/mousedb/context_processors.py
src/mousedb/custom_fields.py
src/mousedb/localsettings.py
src/mousedb/localsettings_empty.py
src/mousedb/manage.py
src/mousedb/settings.py
src/mousedb/urls.py
src/mousedb/views.py
src/mousedb.egg-info/PKG-INFO
src/mousedb.egg-info/SOURCES.txt
src/mousedb.egg-info/dependency_links.txt
src/mousedb.egg-info/requires.txt
src/mousedb.egg-info/top_level.txt
src/mousedb/animal/__init__.py
src/mousedb/animal/admin.py
src/mousedb/animal/filters.py
src/mousedb/animal/forms.py
src/mousedb/animal/lookups.py
src/mousedb/animal/models.py
src/mousedb/animal/tests.py
src/mousedb/animal/views.py
src/mousedb/animal/templatetags/__init__.py
src/mousedb/animal/templatetags/custom_filters.py
src/mousedb/animal/urls/__init__.py
src/mousedb/animal/urls/breeding.py
src/mousedb/animal/urls/cage.py
src/mousedb/animal/urls/date.py
src/mousedb/animal/urls/mouse.py
src/mousedb/animal/urls/strain.py
src/mousedb/animal/urls/todo.py
src/mousedb/data/__init__.py
src/mousedb/data/admin.py
src/mousedb/data/forms.py
src/mousedb/data/models.py
src/mousedb/data/views.py
src/mousedb/data/urls/__init__.py
src/mousedb/data/urls/experiment.py
src/mousedb/data/urls/parameter.py
src/mousedb/data/urls/study.py
src/mousedb/data/urls/treatment.py
src/mousedb/groups/__init__.py
src/mousedb/groups/admin.py
src/mousedb/groups/models.py
src/mousedb/groups/tests.py
src/mousedb/groups/views.py
src/mousedb/timed_mating/__init__.py
src/mousedb/timed_mating/admin.py
src/mousedb/timed_mating/forms.py
src/mousedb/timed_mating/models.py
src/mousedb/timed_mating/tests.py
src/mousedb/timed_mating/urls.py
src/mousedb/timed_mating/views.py