Metadata-Version: 1.0
Name: mousedb
Version: 0.2.1
Summary: A web based application for storage and organization of data regarding experimental animals
Home-page: http://github.com/davebridges/mousedb
Author: Dave Bridges
Author-email: dave.bridges@gmail.com
License: BSD
Platform: UNKNOWN
Classifier: Development Status :: 4 - Beta
Classifier: Framework :: Django
Classifier: Intended Audience :: Developers
Classifier: License :: OSI Approved :: BSD License
Classifier: Operating System :: OS Independent
Classifier: Programming Language :: Python
Classifier: Topic :: Internet :: WWW/HTTP
